{
    "themes": [
        {
            "theme": "dark",
            "background": "#18191A",
            "shape": "rect",
            "color": "#242526",
            "onclick": "#000000",
            "text": "#ffffff",
            "transparent": false
        },
        {
            "theme": "light blue",
            "background": "#40c4ff",
            "shape": "rect",
            "color": "#ffffff",
            "onclick": "#40c4ff",
            "text": "#40c4ff",
            "transparent": false
        },
        {
            "theme": "oreo",
            "background": "#ffffff",
            "shape": "circle",
            "color": "#242526",
            "onclick": "#b0b3b8",
            "text": "#ffffff",
            "transparent": false
        },
        {
            "theme": "transparent",
            "background": "#6a6a6a",
            "shape": "circle",
            "color": "#f8f8ff",
            "onclick": {
                "transparent": false
            },
            "text": "#000000",
            "transparent": true
        },
        {
            "theme": "light",
            "background": "#fefefa",
            "shape": "circle",
            "color": "#d9d9d9",
            "onclick": "#b3b3b3",
            "text": "#000000",
            "transparent": false
        },
        {
            "theme": "red",
            "background": "#f71e0e",
            "shape": "circle",
            "color": "#fa857c",
            "onclick": "#c51306",
            "text": "#000000",
            "transparent": false
        }
    ]
}